sfn_exec_mcp/__init__.py
sfn_exec_mcp/server.py
sfn_exec_mcp-0.1.0.dist-info/METADATA
sfn_exec_mcp-0.1.0.dist-info/WHEEL
sfn_exec_mcp-0.1.0.dist-info/entry_points.txt
sfn_exec_mcp-0.1.0.dist-info/top_level.txt
sfn_exec_mcp-0.1.0.dist-info/RECORD
