Metadata-Version: 2.4
Name: sfn-exec-mcp
Version: 0.1.0
Summary: AWS Step Functions Execution MCP Server
Requires-Dist: fastmcp
Requires-Dist: boto3
